esn_tool/__init__.py
esn_tool/cli.py
esn_tool/commands/__init__.py
esn_tool/commands/acm.py
esn_tool/commands/config.py
esn_tool/commands/git.py
esn_tool/commands/gitlab.py
esn_tool/commands/init.py
esn_tool/commands/run.py
esn_tool/commands/tools.py
esn_tool/services/__init__.py
esn_tool/services/ai.py
esn_tool/services/git_service.py
esn_tool/ui/__init__.py
esn_tool/ui/file_selector.py
esn_tool/ui/tools_app.py
esn_tool/ui/widgets/tool_content.py
esn_tool/ui/widgets/tool_list.py
esn_tool/ui/widgets/common/__init__.py
esn_tool/ui/widgets/tools/__init__.py
esn_tool/ui/widgets/tools/config_tool.py
esn_tool/ui/widgets/tools/git_tool.py
esn_tool/ui/widgets/tools/system_info_tool.py
esn_tool/ui/widgets/tools/tool_base.py
esn_tool/ui/widgets/tools/tool_registry.py
esn_tool/utils/__init__.py
esn_tool/utils/config.py
esn_tool/utils/console.py
esn_tool/utils/project_config.py
esn_tool/utils/style.py
esn_tool-0.1.1.dist-info/METADATA
esn_tool-0.1.1.dist-info/WHEEL
esn_tool-0.1.1.dist-info/entry_points.txt
esn_tool-0.1.1.dist-info/licenses/LICENSE
esn_tool-0.1.1.dist-info/RECORD
