Metadata-Version: 2.4
Name: esn-tool
Version: 0.1.1
Summary: 一个用于管理生产项目的 CLI 工具
Author: StevenLiu
License: MIT
License-File: LICENSE
Keywords: cli,devtools,project-management
Classifier: Development Status :: 3 - Alpha
Classifier: Environment :: Console
Classifier: Intended Audience :: Developers
Classifier: License :: OSI Approved :: MIT License
Classifier: Programming Language :: Python :: 3.12
Classifier: Topic :: Software Development :: Build Tools
Requires-Python: >=3.12
Requires-Dist: click>=8.1.0
Requires-Dist: httpx>=0.27.0
Requires-Dist: questionary>=2.0.0
Requires-Dist: rich>=13.0.0
Requires-Dist: textual>=0.47.0
